mlserver_openvino/__init__.py
mlserver_openvino/convert.py
mlserver_openvino/model.py
mlserver_openvino/transformer.py
mlserver_openvino/version.py
mlserver_openvino/codecs/__init__.py
mlserver_openvino/codecs/json_gzip_base64.py
mlserver_openvino/codecs/lib.py
mlserver_openvino/codecs/numpy_gzip.py
mlserver_openvino/custom_transformers/__init__.py
mlserver_openvino/custom_transformers/dumpy.py
mlserver_openvino-0.4.10.dist-info/LICENSE
mlserver_openvino-0.4.10.dist-info/METADATA
mlserver_openvino-0.4.10.dist-info/WHEEL
mlserver_openvino-0.4.10.dist-info/top_level.txt
mlserver_openvino-0.4.10.dist-info/RECORD
