Metadata-Version: 2.1
Name: mlserver_openvino
Version: 0.4.10
Summary: Openvino runtime for MLServer
Home-page: https://github.com/gawsoftpl/mlserver-openvino
Author: Gawsoft
Author-email: biuro@gawsoft.pl
License: Apache 2.0
Requires-Python: >=3.8
License-File: LICENSE
Requires-Dist: mlserver
Requires-Dist: kserve
Requires-Dist: openvino
Requires-Dist: kubernetes
